heap/__init__.py
heap/error.py
heap/heap.py
hipster/__init__.py
hipster/error.py
hipster/heap.py
hipster/max_heap.py
hipster/min_heap.py
hipster-3.0.5.dist-info/METADATA
hipster-3.0.5.dist-info/WHEEL
hipster-3.0.5.dist-info/top_level.txt
hipster-3.0.5.dist-info/RECORD
