Metadata-Version: 2.1
Name: hipster
Version: 3.0.5
Summary: A thread safe implementation of the MinHeap and MaxHeap
Home-page: https://github.com/soumasish/hipster
Author: Soumasish Goswami
Author-email: soumasish@gmail.com
License: MIT
Platform: UNKNOWN
Classifier: License :: OSI Approved :: MIT License
Classifier: Programming Language :: Python :: 3
Classifier: Programming Language :: Python :: 3.7
Requires-Dist: readerwriterlock
